docbox/__init__.py
docbox/bounding_box.py
docbox/tests/test_bounding_box.py
docbox-0.0.2.dist-info/LICENSE
docbox-0.0.2.dist-info/WHEEL
docbox-0.0.2.dist-info/METADATA
docbox-0.0.2.dist-info/RECORD
